{
  "dias": [
    {
      "data": "2026-05-21",
      "lotofacil": [
        "img/2026-05-21-lf_01.png",
        "img/2026-05-21-lf_02.png",
        "img/2026-05-21-lf_03.png",
        "img/2026-05-21-lf_04.png",
        "img/2026-05-21-lf_05.png"
      ],
      "lotomania": [],
      "megasena": []
    },
    {
      "data": "2026-05-20",
      "lotofacil": [
        "img/2026-05-20-lf_01.png",
        "img/2026-05-20-lf_02.png",
        "img/2026-05-20-lf_03.png",
        "img/2026-05-20-lf_04.png",
        "img/2026-05-20-lf_05.png"
      ],
      "lotomania": [
        "img/2026-05-20-lm_01.png",
        "img/2026-05-20-lm_02.png",
        "img/2026-05-20-lm_03.png",
        "img/2026-05-20-lm_04.png"
      ],
      "megasena": []
    },
    {
      "data": "2026-05-19",
      "lotofacil": [
        "img/2026-05-19-lf_01.png",
        "img/2026-05-19-lf_02.png",
        "img/2026-05-19-lf_03.png",
        "img/2026-05-19-lf_04.png",
        "img/2026-05-19-lf_05.png"
      ],
      "lotomania": [],
      "megasena": []
    },
    {
      "data": "2026-05-18",
      "lotofacil": [
        "img/2026-05-18-lf_01.png",
        "img/2026-05-18-lf_02.png",
        "img/2026-05-18-lf_03.png",
        "img/2026-05-18-lf_04.png",
        "img/2026-05-18-lf_05.png"
      ],
      "lotomania": [
        "img/2026-05-18-lm_01.png",
        "img/2026-05-18-lm_02.png",
        "img/2026-05-18-lm_03.png",
        "img/2026-05-18-lm_04.png",
        "img/2026-05-18-lm_05.png"
      ],
      "megasena": []
    },
    {
      "data": "2026-05-16",
      "lotofacil": [
        "img/2026-05-16-lf_01.png",
        "img/2026-05-16-lf_02.png",
        "img/2026-05-16-lf_03.png",
        "img/2026-05-16-lf_04.png",
        "img/2026-05-16-lf_05.png"
      ],
      "lotomania": [
        "img/2026-05-16-lm_01.png",
        "img/2026-05-16-lm_02.png",
        "img/2026-05-16-lm_03.png",
        "img/2026-05-16-lm_04.png"
      ],
      "megasena": [
        "img/2026-05-16-ms_01.png",
        "img/2026-05-16-ms_02.png",
        "img/2026-05-16-ms_03.png"
      ]
    },
    {
      "data": "2026-05-14",
      "lotofacil": [
        "img/2026-05-14-lf_01.png",
        "img/2026-05-14-lf_02.png",
        "img/2026-05-14-lf_03.png",
        "img/2026-05-14-lf_04.png",
        "img/2026-05-14-lf_05.png"
      ],
      "lotomania": [],
      "megasena": [
        "img/2026-05-14-ms_01.png",
        "img/2026-05-14-ms_02.png",
        "img/2026-05-14-ms_03.png"
      ]
    },
    {
      "data": "2026-05-13",
      "lotofacil": [
        "img/2026-05-13-lf_01.png",
        "img/2026-05-13-lf_02.png",
        "img/2026-05-13-lf_03.png",
        "img/2026-05-13-lf_04.png",
        "img/2026-05-13-lf_05.png"
      ],
      "lotomania": [
        "img/2026-05-13-lm_01.png",
        "img/2026-05-13-lm_02.png",
        "img/2026-05-13-lm_03.png",
        "img/2026-05-13-lm_04.png",
        "img/2026-05-13-lm_05.png"
      ],
      "megasena": []
    },
    {
      "data": "2026-05-12",
      "lotofacil": [
        "img/2026-05-12-lf_01.png",
        "img/2026-05-12-lf_02.png",
        "img/2026-05-12-lf_03.png",
        "img/2026-05-12-lf_04.png",
        "img/2026-05-12-lf_05.png"
      ],
      "lotomania": [],
      "megasena": [
        "img/2026-05-12-ms_01.png",
        "img/2026-05-12-ms_02.png",
        "img/2026-05-12-ms_03.png"
      ]
    },
    {
      "data": "2026-05-11",
      "lotofacil": [
        "img/2026-05-11-lf_01.png",
        "img/2026-05-11-lf_02.png",
        "img/2026-05-11-lf_03.png",
        "img/2026-05-11-lf_04.png",
        "img/2026-05-11-lf_05.png"
      ],
      "lotomania": [
        "img/2026-05-11-lm_01.png",
        "img/2026-05-11-lm_02.png",
        "img/2026-05-11-lm_03.png",
        "img/2026-05-11-lm_04.png",
        "img/2026-05-11-lm_05.png"
      ],
      "megasena": []
    },
    {
      "data": "2026-05-09",
      "lotofacil": [
        "img/2026-05-09-lf_01.png",
        "img/2026-05-09-lf_02.png",
        "img/2026-05-09-lf_03.png",
        "img/2026-05-09-lf_04.png",
        "img/2026-05-09-lf_05.png"
      ],
      "lotomania": [],
      "megasena": [
        "img/2026-05-09-ms_01.png",
        "img/2026-05-09-ms_02.png",
        "img/2026-05-09-ms_03.png"
      ]
    }
  ]
}